{
  "system_id": "AGI-KERNEL_v7.5.0_Synergy",
  "status": "Evolving - Cycle 1 Initiation",
  "active_branch": "main",
  "repo_scale_files": 2300,
  "last_cycle_updated": 0,
  "maturity_snapshot": 0.0,
  "runtime_registry_status": "Operational - First emergent capability invented",
  "core_capabilities": {
    "navigation_score": 3, 
    "logic_score": 2,
    "memory_score": 2,
    "emergent_count": 1
  },
  "metrics_history": [
    {
      "cycle": 0,
      "nav": 2,
      "log": 2,
      "mem": 2,
      "emerge": 0,
      "tools_used": 0
    }
  ],
  "tool_utilization_rate": 0.0,
  "active_emergent_capabilities": []
}