{
  "description": "Defines absolute governance thresholds, failure response policies, and systemic risk controls.",
  "risk_policy": {
    "default_weight": 0.1,
    "max_tolerable_increase": 0.05,
    "reporting_frequency_hz": 1.0,
    "metrics_tracked": [
      "systemic_risk_index",
      "trust_deviation",
      "resource_exhaustion_rate"
    ]
  },
  "governance_thresholds": {
    "TRUST_DEVIATION": {
      "id": "S-01",
      "limit": 0.85,
      "type": "min_floor",
      "severity": "CRITICAL",
      "action_plan": "Execute Trust Reconciliation Protocol (TRP-001). Immediate pause of all external interfaces.",
      "description": "Minimum required Trust Score (AOC Mandate S-01)."
    },
    "SYSTEMIC_RISK": {
      "id": "S-02",
      "limit": 0.15,
      "type": "max_ceiling",
      "severity": "HIGH",
      "action_plan": "Trigger Risk Mitigation Module (RMM). Initiate resource reallocation to stabilize indices.",
      "description": "Maximum allowed systemic risk exposure (AOC Mandate S-02)."
    },
    "COMPUTATIONAL_OVERSIGHT": {
      "id": "A-05",
      "limit": 1000000.0,
      "type": "max_ceiling",
      "severity": "MODERATE",
      "action_plan": "Log and throttle non-essential processes. Review allocation policy.",
      "description": "Hard limit on per-epoch resource allocation."
    }
  }
}